{"cameraMode":{"drawMode":0,"name":"Shaded","section":"Shading Mode"},"sceneLighting":true,"audioPlay":false,"sceneViewState":{"m_AlwaysRefresh":false,"showFog":true,"showSkybox":true,"showFlares":true,"showImageEffects":true,"showParticleSystems":true,"showVisualEffectGraphs":true,"m_FxEnabled":true},"in2DMode":false,"pivot":{"x":-143.91148376464845,"y":-139.8258514404297,"z":219.93365478515626},"rotation":{"x":0.2557695508003235,"y":-0.2569648325443268,"z":0.07049153000116348,"w":0.9293591380119324},"size":173.8616943359375,"orthographic":false}